matrix11x7/__init__.py
matrix11x7/is31fl3731.py
matrix11x7/api/__init__.py
matrix11x7/api/action.py
matrix11x7/api/http.py
matrix11x7/api/stoppablethread.py
matrix11x7/fonts/__init__.py
matrix11x7/fonts/font3x5.py
matrix11x7/fonts/font5x5.py
matrix11x7/fonts/font5x7.py
matrix11x7/fonts/font5x7smoothed.py
matrix11x7/fonts/font5x7unicode.py
matrix11x7-0.0.1.dist-info/LICENSE.txt
matrix11x7-0.0.1.dist-info/METADATA
matrix11x7-0.0.1.dist-info/WHEEL
matrix11x7-0.0.1.dist-info/top_level.txt
matrix11x7-0.0.1.dist-info/RECORD
